Metadata-Version: 2.1
Name: dowolnaNazwa
Version: 1.0.1
Summary: Pakiet testowy
Home-page: http://test.pl
License: UNKNOWN
Platform: UNKNOWN
